mofreinforce/__init__.py
mofreinforce/run_generator.py
mofreinforce/run_predictor.py
mofreinforce/run_reinforce.py
mofreinforce/cli/__init__.py
mofreinforce/cli/download.py
mofreinforce/cli/main.py
mofreinforce/generator/__init__.py
mofreinforce/generator/config_generator.py
mofreinforce/generator/datamodule.py
mofreinforce/generator/dataset.py
mofreinforce/generator/module.py
mofreinforce/generator/objectives.py
mofreinforce/generator/transformer/__init__.py
mofreinforce/generator/transformer/attention.py
mofreinforce/generator/transformer/layers.py
mofreinforce/generator/transformer/transformer.py
mofreinforce/predictor/__init__.py
mofreinforce/predictor/baseline_model.py
mofreinforce/predictor/config_predictor.py
mofreinforce/predictor/datamodule.py
mofreinforce/predictor/dataset.py
mofreinforce/predictor/gadgets.py
mofreinforce/predictor/heads.py
mofreinforce/predictor/module.py
mofreinforce/predictor/objectives.py
mofreinforce/predictor/transformer.py
mofreinforce/reinforce/__init__.py
mofreinforce/reinforce/config_reinforce.py
mofreinforce/reinforce/module.py
mofreinforce/reinforce/reinforce.py
mofreinforce/utils/__init__.py
mofreinforce/utils/download.py
mofreinforce/utils/gadgets.py
mofreinforce/utils/metrics.py
mofreinforce/utils/module_utils.py
mofreinforce-1.0.1.dist-info/LICENSE
mofreinforce-1.0.1.dist-info/METADATA
mofreinforce-1.0.1.dist-info/WHEEL
mofreinforce-1.0.1.dist-info/entry_points.txt
mofreinforce-1.0.1.dist-info/top_level.txt
mofreinforce-1.0.1.dist-info/RECORD
