Metadata-Version: 2.1
Name: mofreinforce
Version: 1.0.1
Summary: mofreinforce
Download-URL: https://github.com/hspark1212/MOFreinforce
Author: Hyunsoo Park
Author-email: phs68660888@gmail.com
Requires-Python: >=3.8
License-File: LICENSE
Requires-Dist: pytorch-lightning (==1.8.0)
Requires-Dist: torchmetrics (==0.9.0)
Requires-Dist: sacred (>=0.8.2)
Requires-Dist: numpy (>=1.22.4)
Requires-Dist: sklearn (>=0.0)
Requires-Dist: scikit-learn (>=1.1.1)
Requires-Dist: tqdm (>=4.64.0)
Requires-Dist: timm (>=0.5.4)
Requires-Dist: transformers (>=4.20.1)
Requires-Dist: SmilesPE (>=0.0.3)
Requires-Dist: rdkit
Requires-Dist: wget
Provides-Extra: docs
Requires-Dist: sphinx ; extra == 'docs'
Requires-Dist: livereload ; extra == 'docs'
Requires-Dist: myst-parser ; extra == 'docs'
